hsdustconverter/__init__.py
hsdustconverter/hsdustconverter.py
hsdustconverter-0.2.1.dist-info/AUTHORS.rst
hsdustconverter-0.2.1.dist-info/LICENSE
hsdustconverter-0.2.1.dist-info/METADATA
hsdustconverter-0.2.1.dist-info/WHEEL
hsdustconverter-0.2.1.dist-info/top_level.txt
hsdustconverter-0.2.1.dist-info/RECORD
