Metadata-Version: 2.1
Name: hsdustconverter
Version: 0.2.1
Summary: Helps to convert duplicate cards into dust in Hearthstone
Home-page: https://github.com/savkorlev/hsdustconverter
Author: Evgenii Korsakov
Author-email: sev2384@gmail.com
License: MIT license
Keywords: hsdustconverter
Platform: UNKNOWN
Classifier: Development Status :: 2 - Pre-Alpha
Classifier: Intended Audience :: Developers
Classifier: License :: OSI Approved :: MIT License
Classifier: Natural Language :: English
Classifier: Programming Language :: Python :: 3
Classifier: Programming Language :: Python :: 3.6
Classifier: Programming Language :: Python :: 3.7
Classifier: Programming Language :: Python :: 3.8
Requires-Python: >=3.6
License-File: LICENSE
License-File: AUTHORS.rst
